ezssh/__init__.py
ezssh/client.py
ezssh/exceptions.py
ezssh/models.py
ezssh-0.0.9.dist-info/licenses/LICENSE
ezssh-0.0.9.dist-info/licenses/NOTICE
ezssh-0.0.9.dist-info/METADATA
ezssh-0.0.9.dist-info/WHEEL
ezssh-0.0.9.dist-info/top_level.txt
ezssh-0.0.9.dist-info/RECORD
