Metadata-Version: 2.4
Name: ezssh
Version: 0.0.9
Summary: A lightweight, ergonomic SSH library.
Author: Noah Black
License: Apache-2.0
Keywords: ssh,automation,remote-execution,batch,paramiko,infrastructure,devops,control-plane
Classifier: Development Status :: 4 - Beta
Classifier: Intended Audience :: Developers
Classifier: Topic :: System :: Systems Administration
Classifier: Topic :: Software Development :: Libraries
Classifier: License :: OSI Approved :: Apache Software License
Classifier: Programming Language :: Python :: 3
Requires-Python: >=3.9
License-File: LICENSE
License-File: NOTICE
Requires-Dist: paramiko>=3.0
Dynamic: license-file
